PyRandomPassword/PyRandomPassword.py
py_random_password-0.0.4.dist-info/LICENSE
py_random_password-0.0.4.dist-info/METADATA
py_random_password-0.0.4.dist-info/WHEEL
py_random_password-0.0.4.dist-info/top_level.txt
py_random_password-0.0.4.dist-info/RECORD
