Metadata-Version: 2.1
Name: py-random-password
Version: 0.0.4
Summary: generate a random password using python.
Home-page: https://github.com/sujitmandal/py-random-password
Author: Sujit Mandal
Author-email: mandals974@gmail.com
License: MIT
Platform: UNKNOWN
Classifier: License :: OSI Approved :: MIT License
Classifier: Programming Language :: Python :: 2.7
Classifier: Programming Language :: Python :: 3.0
Classifier: Programming Language :: Python :: 3.5
Classifier: Programming Language :: Python :: 3.6
Classifier: Programming Language :: Python :: 3.7
Classifier: Programming Language :: Python :: 3.8
Classifier: Programming Language :: Python :: 3.9
